oke_mcp_server/__init__.py
oke_mcp_server/auth.py
oke_mcp_server/config.py
oke_mcp_server/config_store.py
oke_mcp_server/main.py
oke_mcp_server/oci_auth.py
oke_mcp_server/oke_auth.py
oke_mcp_server/tools/__init__.py
oke_mcp_server/tools/events.py
oke_mcp_server/tools/k8s.py
oke_mcp_server/tools/metrics.py
oke_mcp_server/tools/oke.py
oke_mcp_server/tools/oke_cluster.py
oke_mcp_server-0.2.0.dist-info/licenses/LICENSE
oke_mcp_server-0.2.0.dist-info/METADATA
oke_mcp_server-0.2.0.dist-info/WHEEL
oke_mcp_server-0.2.0.dist-info/entry_points.txt
oke_mcp_server-0.2.0.dist-info/top_level.txt
oke_mcp_server-0.2.0.dist-info/RECORD
