Metadata-Version: 2.4
Name: oke-mcp-server
Version: 0.2.0
Summary: Minimal MCP server for managing Oracle OKE & Kubernetes, optimized for LLMs.
Author: Ron Sevet
License: Apache-2.0
Project-URL: Homepage, https://github.com/ronsevetoci/oke-mcp-server
Project-URL: Issues, https://github.com/ronsevetoci/oke-mcp-server/issues
Project-URL: Source, https://github.com/ronsevetoci/oke-mcp-server
Keywords: MCP,Oracle,OKE,Kubernetes,LLM,DevTools
Classifier: Programming Language :: Python :: 3
Classifier: Programming Language :: Python :: 3 :: Only
Classifier: Programming Language :: Python :: 3.9
Classifier: Programming Language :: Python :: 3.10
Classifier: Programming Language :: Python :: 3.11
Classifier: Programming Language :: Python :: 3.12
Classifier: Programming Language :: Python :: 3.13
Classifier: License :: OSI Approved :: Apache Software License
Classifier: Environment :: Console
Classifier: Intended Audience :: Developers
Classifier: Topic :: Software Development :: Libraries :: Application Frameworks
Requires-Python: >=3.9
License-File: LICENSE
Requires-Dist: mcp>=1.1.0
Requires-Dist: mcp[cli]>=1.1.0
Requires-Dist: fastmcp>=0.4.0
Requires-Dist: oci>=2.157.1
Requires-Dist: kubernetes>=28.1.0
Requires-Dist: pyyaml>=6.0.1
Provides-Extra: dev
Requires-Dist: ruff>=0.5.0; extra == "dev"
Requires-Dist: mypy>=1.10.0; extra == "dev"
Requires-Dist: pytest>=8.2.0; extra == "dev"
Requires-Dist: build>=1.2.1; extra == "dev"
Requires-Dist: twine>=5.1.1; extra == "dev"
Requires-Dist: uv>=0.4.0; extra == "dev"
Dynamic: license-file
